lightning_node_prediction/__init__.py
lightning_node_prediction/_modidx.py
lightning_node_prediction/lightning_prediction.py
lightning_node_prediction-0.0.4.dist-info/LICENSE
lightning_node_prediction-0.0.4.dist-info/METADATA
lightning_node_prediction-0.0.4.dist-info/WHEEL
lightning_node_prediction-0.0.4.dist-info/entry_points.txt
lightning_node_prediction-0.0.4.dist-info/top_level.txt
lightning_node_prediction-0.0.4.dist-info/RECORD
